_diffcp.cp36-win_amd64.pyd
diffcp/__init__.py
diffcp/cone_program.py
diffcp/cones.py
diffcp/utils.py
tests/__init__.py
tests/test_cone_prog_diff.py
tests/test_ecos.py
tests/test_scs.py
DCSPrivtestPack-1.0.21.dist-info/LICENSE
DCSPrivtestPack-1.0.21.dist-info/METADATA
DCSPrivtestPack-1.0.21.dist-info/WHEEL
DCSPrivtestPack-1.0.21.dist-info/top_level.txt
DCSPrivtestPack-1.0.21.dist-info/RECORD
