Metadata-Version: 2.1
Name: DCSPrivtestPack
Version: 1.0.21
Summary: UNKNOWN
Home-page: https://github.com/dance858/TestPypi1
Author: DC
License: Apache License, Version 2.0
Platform: UNKNOWN
Classifier: Programming Language :: Python :: 3
License-File: LICENSE
Requires-Dist: numpy (>=1.15)
Requires-Dist: scs (>=2.0.2)
Requires-Dist: scipy (>=1.1.0)
Requires-Dist: pybind11 (>=2.4)
Requires-Dist: threadpoolctl (>=1.1)
Requires-Dist: ecos
